README.txt
setup.py
ripy/__init__.py
ripy/examples_ripy.py
ripy/pvl_scraper.py
ripy/ripy_dbs.py
ripy/ripy_objects.py
ripy.egg-info/PKG-INFO
ripy.egg-info/SOURCES.txt
ripy.egg-info/dependency_links.txt
ripy.egg-info/requires.txt
ripy.egg-info/top_level.txt