Metadata-Version: 1.0
Name: ripy
Version: 0.0.7
Summary: Parsing of refractive index data, designed to be used with the tmmpy package.
Home-page: https://git.kern.phys.au.dk/SunTune/ripy/
Author: Emil Haldrup Eriksen
Author-email: emher@au.dk
License: MIT
Platform: any
